hello_world_kas/__init__.py
hello_world_kas/main.py
hello_world_kas-0.0.4.dist-info/METADATA
hello_world_kas-0.0.4.dist-info/WHEEL
hello_world_kas-0.0.4.dist-info/entry_points.txt
hello_world_kas-0.0.4.dist-info/top_level.txt
hello_world_kas-0.0.4.dist-info/RECORD
